pyg_multiagent/__init__.py
pyg_multiagent/baselines/__init__.py
pyg_multiagent/baselines/ddpg.py
pyg_multiagent/baselines/ddpg_config_drone.py
pyg_multiagent/baselines/ddpg_config_dubins_car.py
pyg_multiagent/baselines/ddpg_config_multi_dynamic_dubins.py
pyg_multiagent/baselines/ddpg_config_ur5.py
pyg_multiagent/baselines/gpg.py
pyg_multiagent/baselines/gpg_config.py
pyg_multiagent/baselines/inference-baselines.py
pyg_multiagent/baselines/macbf.py
pyg_multiagent/baselines/macbf_config_drone.py
pyg_multiagent/baselines/macbf_config_dubins_car.py
pyg_multiagent/baselines/macbf_config_multi_dynamic_dubins.py
pyg_multiagent/baselines/macbf_config_ur5.py
pyg_multiagent/baselines/ppo.py
pyg_multiagent/baselines/ppo_config.py
pyg_multiagent/configs/drone/v0.py
pyg_multiagent/configs/drone/v1.py
pyg_multiagent/configs/drone/v10.py
pyg_multiagent/configs/drone/v11.py
pyg_multiagent/configs/drone/v12.py
pyg_multiagent/configs/drone/v13.py
pyg_multiagent/configs/drone/v14.py
pyg_multiagent/configs/drone/v15.py
pyg_multiagent/configs/drone/v16.py
pyg_multiagent/configs/drone/v17.py
pyg_multiagent/configs/drone/v18.py
pyg_multiagent/configs/drone/v19.py
pyg_multiagent/configs/drone/v2.py
pyg_multiagent/configs/drone/v20.py
pyg_multiagent/configs/drone/v21.py
pyg_multiagent/configs/drone/v22.py
pyg_multiagent/configs/drone/v23.py
pyg_multiagent/configs/drone/v24.py
pyg_multiagent/configs/drone/v25.py
pyg_multiagent/configs/drone/v26.py
pyg_multiagent/configs/drone/v27.py
pyg_multiagent/configs/drone/v28.py
pyg_multiagent/configs/drone/v29.py
pyg_multiagent/configs/drone/v3.py
pyg_multiagent/configs/drone/v30.py
pyg_multiagent/configs/drone/v31.py
pyg_multiagent/configs/drone/v32.py
pyg_multiagent/configs/drone/v33.py
pyg_multiagent/configs/drone/v34.py
pyg_multiagent/configs/drone/v35.py
pyg_multiagent/configs/drone/v36.py
pyg_multiagent/configs/drone/v37.py
pyg_multiagent/configs/drone/v38.py
pyg_multiagent/configs/drone/v39.py
pyg_multiagent/configs/drone/v4.py
pyg_multiagent-0.0.5.dist-info/LICENSE
pyg_multiagent-0.0.5.dist-info/METADATA
pyg_multiagent-0.0.5.dist-info/WHEEL
pyg_multiagent-0.0.5.dist-info/top_level.txt
pyg_multiagent-0.0.5.dist-info/RECORD
