Metadata-Version: 2.1
Name: pyg-multiagent
Version: 0.0.5
Summary: Python Package for Multi-Agent Learning
Home-page: https://github.com/rainorangelemon/pytorch_geometric_multiagent
Download-URL: https://github.com/rainorangelemon/pytorch_geometric_multiagent/archive/0.0.5.tar.gz
Author: Chenning Yu
Author-email: Chenning Yu <rainorangelemon@gmail.com>
Project-URL: Homepage, https://github.com/rainorangelemon/pytorch_geometric_multiagent
Project-URL: Bug Tracker, https://github.com/rainorangelemon/pytorch_geometric_multiagent/issues
Keywords: deep-learning,pytorch,geometric-deep-learning,graph-neural-networks,pytorch-geometric,multi-agent
Classifier: Programming Language :: Python :: 3
Classifier: License :: OSI Approved :: MIT License
Classifier: Operating System :: OS Independent
Requires-Python: >=3.8
License-File: LICENSE
Requires-Dist: tqdm
Requires-Dist: numpy
Requires-Dist: matplotlib
Requires-Dist: scipy
Requires-Dist: cvxpy
Requires-Dist: pybullet
Provides-Extra: benchmark
Requires-Dist: wandb ; extra == 'benchmark'
Provides-Extra: dev
Requires-Dist: pytest ; extra == 'dev'
Requires-Dist: pytest-cov ; extra == 'dev'
Requires-Dist: pre-commit ; extra == 'dev'
Provides-Extra: full
Requires-Dist: tqdm ; extra == 'full'
Requires-Dist: numpy ; extra == 'full'
Requires-Dist: matplotlib ; extra == 'full'
Requires-Dist: scipy ; extra == 'full'
Requires-Dist: cvxpy ; extra == 'full'
Requires-Dist: pybullet ; extra == 'full'
Provides-Extra: test
Requires-Dist: pytest ; extra == 'test'
Requires-Dist: pytest-cov ; extra == 'test'
